pynetstring.py
tests/__init__.py
tests/tests.backup.py
tests/tests.py
pynetstring-0.5.dist-info/LICENSE.txt
pynetstring-0.5.dist-info/METADATA
pynetstring-0.5.dist-info/WHEEL
pynetstring-0.5.dist-info/top_level.txt
pynetstring-0.5.dist-info/RECORD
