Metadata-Version: 2.1
Name: pynetstring
Version: 0.5
Summary: A module for encoding and decoding netstrings.
Home-page: https://github.com/rj79/pynetstring
Author: Robert Johansson
Author-email: robertrockar@live.com
License: MIT
Platform: UNKNOWN
Classifier: Development Status :: 4 - Beta
Classifier: Intended Audience :: Developers
Classifier: Topic :: Software Development
Classifier: License :: OSI Approved :: MIT License
Classifier: Programming Language :: Python :: 3
Requires-Python: >=3
